{
    "type": "FeatureCollection",
    "features": [
        {
            "type": "Feature",
            "properties": {
                "name": "Queenstown 10k",
                "type": "running"
            },
            "geometry": {
                "type": "LineString",
                "coordinates": [
                    [
                        168.730558,
                        -45.020853
                    ],
                    [
                        168.730703,
                        -45.021014
                    ],
                    [
                        168.730853,
                        -45.021179
                    ],
                    [
                        168.730967,
                        -45.021344
                    ],
                    [
                        168.730989,
                        -45.021531
                    ],
                    [
                        168.730803,
                        -45.021665
                    ],
                    [
                        168.730602,
                        -45.021785
                    ],
                    [
                        168.730488,
                        -45.021984
                    ],
                    [
                        168.730472,
                        -45.022172
                    ],
                    [
                        168.730456,
                        -45.022363
                    ],
                    [
                        168.730453,
                        -45.022570
                    ],
                    [
                        168.730467,
                        -45.022754
                    ],
                    [
                        168.730464,
                        -45.022944
                    ],
                    [
                        168.730505,
                        -45.023137
                    ],
                    [
                        168.730521,
                        -45.023352
                    ],
                    [
                        168.730539,
                        -45.023553
                    ],
                    [
                        168.730600,
                        -45.023758
                    ],
                    [
                        168.730736,
                        -45.023919
                    ],
                    [
                        168.730982,
                        -45.024029
                    ],
                    [
                        168.731244,
                        -45.024101
                    ],
                    [
                        168.731532,
                        -45.024123
                    ],
                    [
                        168.731701,
                        -45.024268
                    ],
                    [
                        168.731793,
                        -45.024464
                    ],
                    [
                        168.731795,
                        -45.024672
                    ],
                    [
                        168.731792,
                        -45.024858
                    ],
                    [
                        168.731782,
                        -45.025042
                    ],
                    [
                        168.731814,
                        -45.025255
                    ],
                    [
                        168.731903,
                        -45.025442
                    ],
                    [
                        168.731996,
                        -45.025630
                    ],
                    [
                        168.732111,
                        -45.025816
                    ],
                    [
                        168.732211,
                        -45.025995
                    ],
                    [
                        168.732371,
                        -45.026164
                    ],
                    [
                        168.732626,
                        -45.026258
                    ],
                    [
                        168.732843,
                        -45.026344
                    ],
                    [
                        168.732989,
                        -45.026515
                    ],
                    [
                        168.733086,
                        -45.026716
                    ],
                    [
                        168.733172,
                        -45.026916
                    ],
                    [
                        168.733261,
                        -45.027113
                    ],
                    [
                        168.733367,
                        -45.027306
                    ],
                    [
                        168.733426,
                        -45.027514
                    ],
                    [
                        168.733352,
                        -45.027614
                    ],
                    [
                        168.733093,
                        -45.027610
                    ],
                    [
                        168.732863,
                        -45.027516
                    ],
                    [
                        168.732664,
                        -45.027391
                    ],
                    [
                        168.732516,
                        -45.027241
                    ],
                    [
                        168.732372,
                        -45.027079
                    ],
                    [
                        168.732234,
                        -45.026950
                    ],
                    [
                        168.732097,
                        -45.026789
                    ],
                    [
                        168.732001,
                        -45.026621
                    ],
                    [
                        168.731859,
                        -45.026438
                    ],
                    [
                        168.731727,
                        -45.026248
                    ],
                    [
                        168.731664,
                        -45.026053
                    ],
                    [
                        168.731557,
                        -45.025858
                    ],
                    [
                        168.731480,
                        -45.025677
                    ],
                    [
                        168.731399,
                        -45.025481
                    ],
                    [
                        168.731306,
                        -45.025298
                    ],
                    [
                        168.731210,
                        -45.025107
                    ],
                    [
                        168.731101,
                        -45.024936
                    ],
                    [
                        168.731011,
                        -45.024764
                    ],
                    [
                        168.730871,
                        -45.024576
                    ],
                    [
                        168.730794,
                        -45.024397
                    ],
                    [
                        168.730681,
                        -45.024209
                    ],
                    [
                        168.730532,
                        -45.024023
                    ],
                    [
                        168.730411,
                        -45.023852
                    ],
                    [
                        168.730282,
                        -45.023663
                    ],
                    [
                        168.730255,
                        -45.023464
                    ],
                    [
                        168.730198,
                        -45.023271
                    ],
                    [
                        168.730112,
                        -45.023066
                    ],
                    [
                        168.730043,
                        -45.022853
                    ],
                    [
                        168.729994,
                        -45.022644
                    ],
                    [
                        168.729929,
                        -45.022442
                    ],
                    [
                        168.729889,
                        -45.022244
                    ],
                    [
                        168.729807,
                        -45.022043
                    ],
                    [
                        168.729728,
                        -45.021860
                    ],
                    [
                        168.729604,
                        -45.021671
                    ],
                    [
                        168.729486,
                        -45.021486
                    ],
                    [
                        168.729350,
                        -45.021294
                    ],
                    [
                        168.729246,
                        -45.021128
                    ],
                    [
                        168.729118,
                        -45.020968
                    ],
                    [
                        168.728982,
                        -45.020790
                    ],
                    [
                        168.728867,
                        -45.020604
                    ],
                    [
                        168.728727,
                        -45.020452
                    ],
                    [
                        168.728567,
                        -45.020282
                    ],
                    [
                        168.728396,
                        -45.020128
                    ],
                    [
                        168.728269,
                        -45.019960
                    ],
                    [
                        168.728115,
                        -45.019784
                    ],
                    [
                        168.727951,
                        -45.019615
                    ],
                    [
                        168.727807,
                        -45.019442
                    ],
                    [
                        168.727657,
                        -45.019293
                    ],
                    [
                        168.727443,
                        -45.019148
                    ],
                    [
                        168.727274,
                        -45.019014
                    ],
                    [
                        168.727079,
                        -45.018872
                    ],
                    [
                        168.726854,
                        -45.018751
                    ],
                    [
                        168.726652,
                        -45.018599
                    ],
                    [
                        168.726476,
                        -45.018468
                    ],
                    [
                        168.726303,
                        -45.018325
                    ],
                    [
                        168.726094,
                        -45.018176
                    ],
                    [
                        168.725912,
                        -45.018049
                    ],
                    [
                        168.725695,
                        -45.017908
                    ],
                    [
                        168.725487,
                        -45.017798
                    ],
                    [
                        168.725278,
                        -45.017683
                    ],
                    [
                        168.725012,
                        -45.017594
                    ],
                    [
                        168.724765,
                        -45.017504
                    ],
                    [
                        168.724524,
                        -45.017413
                    ],
                    [
                        168.724279,
                        -45.017303
                    ],
                    [
                        168.724048,
                        -45.017216
                    ],
                    [
                        168.723774,
                        -45.017133
                    ],
                    [
                        168.723545,
                        -45.017051
                    ],
                    [
                        168.723301,
                        -45.016937
                    ],
                    [
                        168.723049,
                        -45.016824
                    ],
                    [
                        168.722801,
                        -45.016752
                    ],
                    [
                        168.722551,
                        -45.016691
                    ],
                    [
                        168.722260,
                        -45.016684
                    ],
                    [
                        168.721975,
                        -45.016714
                    ],
                    [
                        168.721701,
                        -45.016781
                    ],
                    [
                        168.721418,
                        -45.016859
                    ],
                    [
                        168.721158,
                        -45.016911
                    ],
                    [
                        168.720870,
                        -45.016965
                    ],
                    [
                        168.720593,
                        -45.017022
                    ],
                    [
                        168.720344,
                        -45.017065
                    ],
                    [
                        168.720077,
                        -45.017137
                    ],
                    [
                        168.719797,
                        -45.017210
                    ],
                    [
                        168.719526,
                        -45.017292
                    ],
                    [
                        168.719263,
                        -45.017359
                    ],
                    [
                        168.718993,
                        -45.017456
                    ],
                    [
                        168.718722,
                        -45.017490
                    ],
                    [
                        168.718434,
                        -45.017510
                    ],
                    [
                        168.718172,
                        -45.017560
                    ],
                    [
                        168.717888,
                        -45.017565
                    ],
                    [
                        168.717619,
                        -45.017584
                    ],
                    [
                        168.717339,
                        -45.017656
                    ],
                    [
                        168.717073,
                        -45.017736
                    ],
                    [
                        168.716847,
                        -45.017831
                    ],
                    [
                        168.716585,
                        -45.017930
                    ],
                    [
                        168.716316,
                        -45.018011
                    ],
                    [
                        168.716079,
                        -45.018107
                    ],
                    [
                        168.715868,
                        -45.018234
                    ],
                    [
                        168.715666,
                        -45.018373
                    ],
                    [
                        168.715484,
                        -45.018526
                    ],
                    [
                        168.715286,
                        -45.018678
                    ],
                    [
                        168.715079,
                        -45.018792
                    ],
                    [
                        168.714835,
                        -45.018893
                    ],
                    [
                        168.714580,
                        -45.018885
                    ],
                    [
                        168.714295,
                        -45.018935
                    ],
                    [
                        168.713997,
                        -45.018972
                    ],
                    [
                        168.713695,
                        -45.018965
                    ],
                    [
                        168.713402,
                        -45.018961
                    ],
                    [
                        168.713121,
                        -45.019005
                    ],
                    [
                        168.712873,
                        -45.019107
                    ],
                    [
                        168.712628,
                        -45.019222
                    ],
                    [
                        168.712384,
                        -45.019338
                    ],
                    [
                        168.712187,
                        -45.019472
                    ],
                    [
                        168.712006,
                        -45.019602
                    ],
                    [
                        168.711828,
                        -45.019740
                    ],
                    [
                        168.711605,
                        -45.019840
                    ],
                    [
                        168.711386,
                        -45.019938
                    ],
                    [
                        168.711150,
                        -45.020019
                    ],
                    [
                        168.710914,
                        -45.020094
                    ],
                    [
                        168.710651,
                        -45.020174
                    ],
                    [
                        168.710356,
                        -45.020238
                    ],
                    [
                        168.710076,
                        -45.020315
                    ],
                    [
                        168.709793,
                        -45.020366
                    ],
                    [
                        168.709519,
                        -45.020434
                    ],
                    [
                        168.709262,
                        -45.020474
                    ],
                    [
                        168.708984,
                        -45.020534
                    ],
                    [
                        168.708691,
                        -45.020594
                    ],
                    [
                        168.708439,
                        -45.020655
                    ],
                    [
                        168.708174,
                        -45.020707
                    ],
                    [
                        168.707898,
                        -45.020739
                    ],
                    [
                        168.707614,
                        -45.020776
                    ],
                    [
                        168.707344,
                        -45.020788
                    ],
                    [
                        168.707056,
                        -45.020775
                    ],
                    [
                        168.706786,
                        -45.020786
                    ],
                    [
                        168.706519,
                        -45.020819
                    ],
                    [
                        168.706252,
                        -45.020889
                    ],
                    [
                        168.706018,
                        -45.020973
                    ],
                    [
                        168.705812,
                        -45.021104
                    ],
                    [
                        168.705652,
                        -45.021280
                    ],
                    [
                        168.705493,
                        -45.021466
                    ],
                    [
                        168.705321,
                        -45.021625
                    ],
                    [
                        168.705138,
                        -45.021754
                    ],
                    [
                        168.704953,
                        -45.021881
                    ],
                    [
                        168.704920,
                        -45.021911
                    ],
                    [
                        168.704700,
                        -45.022032
                    ],
                    [
                        168.704497,
                        -45.022147
                    ],
                    [
                        168.704263,
                        -45.022271
                    ],
                    [
                        168.703999,
                        -45.022372
                    ],
                    [
                        168.703748,
                        -45.022489
                    ],
                    [
                        168.703498,
                        -45.022563
                    ],
                    [
                        168.703284,
                        -45.022683
                    ],
                    [
                        168.703077,
                        -45.022792
                    ],
                    [
                        168.702837,
                        -45.022862
                    ],
                    [
                        168.702574,
                        -45.022948
                    ],
                    [
                        168.702300,
                        -45.022982
                    ],
                    [
                        168.702041,
                        -45.023033
                    ],
                    [
                        168.701825,
                        -45.023163
                    ],
                    [
                        168.701603,
                        -45.023283
                    ],
                    [
                        168.701333,
                        -45.023353
                    ],
                    [
                        168.701082,
                        -45.023439
                    ],
                    [
                        168.700821,
                        -45.023515
                    ],
                    [
                        168.700561,
                        -45.023624
                    ],
                    [
                        168.700306,
                        -45.023720
                    ],
                    [
                        168.700064,
                        -45.023836
                    ],
                    [
                        168.699808,
                        -45.023922
                    ],
                    [
                        168.699543,
                        -45.023993
                    ],
                    [
                        168.699284,
                        -45.024069
                    ],
                    [
                        168.699064,
                        -45.024179
                    ],
                    [
                        168.698860,
                        -45.024293
                    ],
                    [
                        168.698649,
                        -45.024395
                    ],
                    [
                        168.698426,
                        -45.024494
                    ],
                    [
                        168.698199,
                        -45.024609
                    ],
                    [
                        168.697998,
                        -45.024741
                    ],
                    [
                        168.697831,
                        -45.024902
                    ],
                    [
                        168.697706,
                        -45.025083
                    ],
                    [
                        168.697595,
                        -45.025266
                    ],
                    [
                        168.697434,
                        -45.025435
                    ],
                    [
                        168.697218,
                        -45.025560
                    ],
                    [
                        168.696975,
                        -45.025671
                    ],
                    [
                        168.696745,
                        -45.025772
                    ],
                    [
                        168.696496,
                        -45.025877
                    ],
                    [
                        168.696267,
                        -45.025999
                    ],
                    [
                        168.696031,
                        -45.026093
                    ],
                    [
                        168.695796,
                        -45.026185
                    ],
                    [
                        168.695589,
                        -45.026297
                    ],
                    [
                        168.695353,
                        -45.026406
                    ],
                    [
                        168.695107,
                        -45.026498
                    ],
                    [
                        168.694890,
                        -45.026608
                    ],
                    [
                        168.694648,
                        -45.026688
                    ],
                    [
                        168.694486,
                        -45.026732
                    ],
                    [
                        168.694208,
                        -45.026787
                    ],
                    [
                        168.693922,
                        -45.026791
                    ],
                    [
                        168.693670,
                        -45.026877
                    ],
                    [
                        168.693410,
                        -45.026965
                    ],
                    [
                        168.693157,
                        -45.027086
                    ],
                    [
                        168.692916,
                        -45.027151
                    ],
                    [
                        168.692629,
                        -45.027217
                    ],
                    [
                        168.692341,
                        -45.027274
                    ],
                    [
                        168.692065,
                        -45.027344
                    ],
                    [
                        168.691793,
                        -45.027422
                    ],
                    [
                        168.691527,
                        -45.027509
                    ],
                    [
                        168.691250,
                        -45.027578
                    ],
                    [
                        168.691007,
                        -45.027662
                    ],
                    [
                        168.690759,
                        -45.027745
                    ],
                    [
                        168.690532,
                        -45.027850
                    ],
                    [
                        168.690334,
                        -45.027964
                    ],
                    [
                        168.690126,
                        -45.028095
                    ],
                    [
                        168.689908,
                        -45.028231
                    ],
                    [
                        168.689721,
                        -45.028375
                    ],
                    [
                        168.689514,
                        -45.028501
                    ],
                    [
                        168.689288,
                        -45.028642
                    ],
                    [
                        168.689055,
                        -45.028762
                    ],
                    [
                        168.688794,
                        -45.028833
                    ],
                    [
                        168.688562,
                        -45.028933
                    ],
                    [
                        168.688331,
                        -45.029037
                    ],
                    [
                        168.688135,
                        -45.029164
                    ],
                    [
                        168.687924,
                        -45.029316
                    ],
                    [
                        168.687762,
                        -45.029485
                    ],
                    [
                        168.687580,
                        -45.029631
                    ],
                    [
                        168.687388,
                        -45.029787
                    ],
                    [
                        168.687206,
                        -45.029941
                    ],
                    [
                        168.687014,
                        -45.030086
                    ],
                    [
                        168.686834,
                        -45.030213
                    ],
                    [
                        168.686659,
                        -45.030351
                    ],
                    [
                        168.686474,
                        -45.030485
                    ],
                    [
                        168.686266,
                        -45.030625
                    ],
                    [
                        168.686051,
                        -45.030766
                    ],
                    [
                        168.685849,
                        -45.030920
                    ],
                    [
                        168.685645,
                        -45.031066
                    ],
                    [
                        168.685432,
                        -45.031192
                    ],
                    [
                        168.685193,
                        -45.031305
                    ],
                    [
                        168.684990,
                        -45.031440
                    ],
                    [
                        168.684820,
                        -45.031599
                    ],
                    [
                        168.684633,
                        -45.031766
                    ],
                    [
                        168.684462,
                        -45.031914
                    ],
                    [
                        168.684266,
                        -45.032068
                    ],
                    [
                        168.684095,
                        -45.032212
                    ],
                    [
                        168.683905,
                        -45.032366
                    ],
                    [
                        168.683726,
                        -45.032537
                    ],
                    [
                        168.683553,
                        -45.032698
                    ],
                    [
                        168.683382,
                        -45.032865
                    ],
                    [
                        168.683209,
                        -45.033018
                    ],
                    [
                        168.683037,
                        -45.033159
                    ],
                    [
                        168.682867,
                        -45.033318
                    ],
                    [
                        168.682718,
                        -45.033482
                    ],
                    [
                        168.682574,
                        -45.033639
                    ],
                    [
                        168.682432,
                        -45.033816
                    ],
                    [
                        168.682280,
                        -45.033968
                    ],
                    [
                        168.682096,
                        -45.034147
                    ],
                    [
                        168.681883,
                        -45.034297
                    ],
                    [
                        168.681626,
                        -45.034404
                    ],
                    [
                        168.681401,
                        -45.034501
                    ],
                    [
                        168.681155,
                        -45.034607
                    ],
                    [
                        168.680892,
                        -45.034699
                    ],
                    [
                        168.680637,
                        -45.034699
                    ],
                    [
                        168.680366,
                        -45.034699
                    ],
                    [
                        168.680082,
                        -45.034719
                    ],
                    [
                        168.679809,
                        -45.034767
                    ],
                    [
                        168.679506,
                        -45.034792
                    ],
                    [
                        168.679232,
                        -45.034789
                    ],
                    [
                        168.678956,
                        -45.034810
                    ],
                    [
                        168.678681,
                        -45.034829
                    ],
                    [
                        168.678407,
                        -45.034849
                    ],
                    [
                        168.678132,
                        -45.034901
                    ],
                    [
                        168.677863,
                        -45.034933
                    ],
                    [
                        168.677614,
                        -45.034975
                    ],
                    [
                        168.677358,
                        -45.035039
                    ],
                    [
                        168.677101,
                        -45.035131
                    ],
                    [
                        168.676852,
                        -45.035218
                    ],
                    [
                        168.676592,
                        -45.035276
                    ],
                    [
                        168.676353,
                        -45.035361
                    ],
                    [
                        168.676085,
                        -45.035433
                    ],
                    [
                        168.675852,
                        -45.035536
                    ],
                    [
                        168.675593,
                        -45.035637
                    ],
                    [
                        168.675349,
                        -45.035732
                    ],
                    [
                        168.675075,
                        -45.035812
                    ],
                    [
                        168.674824,
                        -45.035860
                    ],
                    [
                        168.674582,
                        -45.035919
                    ],
                    [
                        168.674301,
                        -45.035989
                    ],
                    [
                        168.674062,
                        -45.036058
                    ],
                    [
                        168.673966,
                        -45.036080
                    ],
                    [
                        168.673692,
                        -45.036156
                    ],
                    [
                        168.673406,
                        -45.036218
                    ],
                    [
                        168.673128,
                        -45.036289
                    ],
                    [
                        168.672836,
                        -45.036341
                    ],
                    [
                        168.672559,
                        -45.036392
                    ],
                    [
                        168.672309,
                        -45.036437
                    ],
                    [
                        168.672061,
                        -45.036489
                    ],
                    [
                        168.671809,
                        -45.036531
                    ],
                    [
                        168.671563,
                        -45.036600
                    ],
                    [
                        168.671303,
                        -45.036688
                    ],
                    [
                        168.671047,
                        -45.036669
                    ],
                    [
                        168.670815,
                        -45.036582
                    ],
                    [
                        168.670589,
                        -45.036498
                    ],
                    [
                        168.670331,
                        -45.036400
                    ],
                    [
                        168.670108,
                        -45.036304
                    ],
                    [
                        168.669828,
                        -45.036224
                    ],
                    [
                        168.669565,
                        -45.036145
                    ],
                    [
                        168.669305,
                        -45.036085
                    ],
                    [
                        168.669030,
                        -45.036014
                    ],
                    [
                        168.668752,
                        -45.035969
                    ],
                    [
                        168.668482,
                        -45.035947
                    ],
                    [
                        168.668215,
                        -45.035954
                    ],
                    [
                        168.667913,
                        -45.035952
                    ],
                    [
                        168.667643,
                        -45.035959
                    ],
                    [
                        168.667387,
                        -45.035956
                    ],
                    [
                        168.667110,
                        -45.035967
                    ],
                    [
                        168.666845,
                        -45.035996
                    ],
                    [
                        168.666564,
                        -45.036029
                    ],
                    [
                        168.666292,
                        -45.036065
                    ],
                    [
                        168.666009,
                        -45.036124
                    ],
                    [
                        168.665719,
                        -45.036174
                    ],
                    [
                        168.665436,
                        -45.036226
                    ],
                    [
                        168.665147,
                        -45.036268
                    ],
                    [
                        168.664885,
                        -45.036339
                    ],
                    [
                        168.664639,
                        -45.036426
                    ],
                    [
                        168.664374,
                        -45.036488
                    ],
                    [
                        168.664105,
                        -45.036568
                    ],
                    [
                        168.663864,
                        -45.036655
                    ],
                    [
                        168.663617,
                        -45.036726
                    ],
                    [
                        168.663357,
                        -45.036796
                    ],
                    [
                        168.663113,
                        -45.036875
                    ],
                    [
                        168.662852,
                        -45.036948
                    ],
                    [
                        168.662611,
                        -45.037079
                    ],
                    [
                        168.662432,
                        -45.037222
                    ],
                    [
                        168.662246,
                        -45.037367
                    ],
                    [
                        168.662181,
                        -45.037412
                    ],
                    [
                        168.662030,
                        -45.037586
                    ],
                    [
                        168.661852,
                        -45.037743
                    ],
                    [
                        168.661710,
                        -45.037939
                    ],
                    [
                        168.661631,
                        -45.038144
                    ],
                    [
                        168.661525,
                        -45.038331
                    ],
                    [
                        168.661382,
                        -45.038500
                    ],
                    [
                        168.661219,
                        -45.038657
                    ],
                    [
                        168.661051,
                        -45.038824
                    ],
                    [
                        168.660842,
                        -45.038968
                    ],
                    [
                        168.660590,
                        -45.039073
                    ],
                    [
                        168.660340,
                        -45.039153
                    ],
                    [
                        168.660117,
                        -45.039264
                    ],
                    [
                        168.659961,
                        -45.039442
                    ],
                    [
                        168.659837,
                        -45.039602
                    ],
                    [
                        168.659671,
                        -45.039775
                    ],
                    [
                        168.659434,
                        -45.039903
                    ],
                    [
                        168.659176,
                        -45.039995
                    ],
                    [
                        168.658892,
                        -45.039995
                    ],
                    [
                        168.658652,
                        -45.039926
                    ],
                    [
                        168.658413,
                        -45.039861
                    ],
                    [
                        168.658120,
                        -45.039811
                    ],
                    [
                        168.657873,
                        -45.039743
                    ],
                    [
                        168.657638,
                        -45.039643
                    ],
                    [
                        168.657459,
                        -45.039511
                    ],
                    [
                        168.657280,
                        -45.039330
                    ],
                    [
                        168.657094,
                        -45.039170
                    ],
                    [
                        168.656945,
                        -45.038995
                    ],
                    [
                        168.656916,
                        -45.038793
                    ],
                    [
                        168.656971,
                        -45.038614
                    ],
                    [
                        168.657077,
                        -45.038419
                    ],
                    [
                        168.657196,
                        -45.038251
                    ],
                    [
                        168.657253,
                        -45.038059
                    ],
                    [
                        168.657377,
                        -45.037873
                    ],
                    [
                        168.657549,
                        -45.037735
                    ],
                    [
                        168.657770,
                        -45.037617
                    ],
                    [
                        168.658025,
                        -45.037514
                    ],
                    [
                        168.658256,
                        -45.037413
                    ],
                    [
                        168.658457,
                        -45.037300
                    ],
                    [
                        168.658674,
                        -45.037204
                    ],
                    [
                        168.658912,
                        -45.037101
                    ],
                    [
                        168.659149,
                        -45.036983
                    ],
                    [
                        168.659376,
                        -45.036887
                    ],
                    [
                        168.659595,
                        -45.036748
                    ],
                    [
                        168.659826,
                        -45.036633
                    ],
                    [
                        168.660037,
                        -45.036495
                    ],
                    [
                        168.660069,
                        -45.036475
                    ],
                    [
                        168.660296,
                        -45.036337
                    ],
                    [
                        168.660537,
                        -45.036202
                    ],
                    [
                        168.660764,
                        -45.036072
                    ],
                    [
                        168.661010,
                        -45.035943
                    ],
                    [
                        168.661202,
                        -45.035815
                    ],
                    [
                        168.661400,
                        -45.035675
                    ],
                    [
                        168.661592,
                        -45.035548
                    ],
                    [
                        168.661819,
                        -45.035402
                    ],
                    [
                        168.662036,
                        -45.035251
                    ],
                    [
                        168.662229,
                        -45.035097
                    ],
                    [
                        168.662406,
                        -45.034939
                    ],
                    [
                        168.662506,
                        -45.034772
                    ],
                    [
                        168.662576,
                        -45.034569
                    ],
                    [
                        168.662544,
                        -45.034393
                    ],
                    [
                        168.662334,
                        -45.034255
                    ],
                    [
                        168.662146,
                        -45.034123
                    ],
                    [
                        168.661933,
                        -45.033985
                    ],
                    [
                        168.661736,
                        -45.033861
                    ],
                    [
                        168.661558,
                        -45.033726
                    ],
                    [
                        168.661365,
                        -45.033572
                    ],
                    [
                        168.661150,
                        -45.033420
                    ],
                    [
                        168.660966,
                        -45.033268
                    ],
                    [
                        168.660797,
                        -45.033133
                    ],
                    [
                        168.660613,
                        -45.032982
                    ],
                    [
                        168.660452,
                        -45.032831
                    ],
                    [
                        168.660315,
                        -45.032652
                    ],
                    [
                        168.660090,
                        -45.032518
                    ],
                    [
                        168.659885,
                        -45.032399
                    ],
                    [
                        168.659667,
                        -45.032263
                    ],
                    [
                        168.659495,
                        -45.032113
                    ],
                    [
                        168.659310,
                        -45.031988
                    ],
                    [
                        168.659153,
                        -45.031829
                    ],
                    [
                        168.659029,
                        -45.031643
                    ],
                    [
                        168.659038,
                        -45.031455
                    ],
                    [
                        168.659164,
                        -45.031296
                    ],
                    [
                        168.659282,
                        -45.031113
                    ],
                    [
                        168.659388,
                        -45.030939
                    ],
                    [
                        168.659487,
                        -45.030753
                    ],
                    [
                        168.659609,
                        -45.030567
                    ],
                    [
                        168.659709,
                        -45.030374
                    ],
                    [
                        168.659814,
                        -45.030202
                    ],
                    [
                        168.659893,
                        -45.030007
                    ],
                    [
                        168.659969,
                        -45.029825
                    ],
                    [
                        168.660054,
                        -45.029653
                    ],
                    [
                        168.660137,
                        -45.029465
                    ],
                    [
                        168.660175,
                        -45.029392
                    ],
                    [
                        168.660242,
                        -45.029254
                    ],
                    [
                        168.660258,
                        -45.029232
                    ]
                ]
            }
        }
    ]
}
